utils_gap/__init__.py
utils_gap/extraccion/__init__.py
utils_gap/extraccion/extraer_posiciones.py
utils_gap/fuentes_argentinas/__init__.py
utils_gap/fuentes_argentinas/consulta_api.py
utils_gap/fuentes_argentinas/fuentes_gap.py
utils_gap/gap/__init__.py
utils_gap/gap/calcular_gaps.py
utils_gap/gap/filtrar_gaps.py
utils_gap/gap/argentinos/__init__.py
utils_gap/gap/argentinos/gaps_argentinos.py
utils_gap/postprocesamiento/__init__.py
utils_gap/postprocesamiento/postprocesar.py
utils_gap/postprocesamiento/utils.py
utils_gap/utils/__init__.py
utils_gap/utils/areas.py
utils_gap/utils/fechas.py
utils_gap/utils/log.py
utils_gap/utils/update_layers.py
utils_gap/validacion/__init__.py
utils_gap/validacion/pipeline_validacion.py
utils_gap/validacion/utils.py
utils_gap/validacion/validar_gaps.py
utils_gap/validacion/validadores/__init__.py
utils_gap/validacion/validadores/cantidad_posiciones.py
utils_gap/validacion/validadores/elipse.py
utils_gap/validacion/validadores/severidad.py
utils_gap/validacion/validadores/trayectoria.py
utils_gap/validacion/validadores/velocidad.py
utils_gap/validacion/validadores/zeea.py
utils_gap-0.0.5.dist-info/METADATA
utils_gap-0.0.5.dist-info/WHEEL
utils_gap-0.0.5.dist-info/top_level.txt
utils_gap-0.0.5.dist-info/RECORD
