Metadata-Version: 2.1
Name: utils-gap
Version: 0.0.5
Summary: Utilidades para GAP-PNA-ASA
Home-page: https://example.com
Author: gsabatino
Author-email: gsabatino@example.com
Project-URL: Docs, https://docs.example.com
Classifier: Programming Language :: Python :: 3
Classifier: License :: OSI Approved :: MIT License
Classifier: Operating System :: OS Independent
Requires-Python: >=3.6
